MANIFEST.in
README.rst
setup.cfg
setup.py
versioneer.py
PhilDB.egg-info/PKG-INFO
PhilDB.egg-info/SOURCES.txt
PhilDB.egg-info/dependency_links.txt
PhilDB.egg-info/entry_points.txt
PhilDB.egg-info/requires.txt
PhilDB.egg-info/top_level.txt
phildb/__init__.py
phildb/_version.py
phildb/console.py
phildb/constants.py
phildb/create.py
phildb/database.py
phildb/dbstructures.py
phildb/exceptions.py
phildb/log_handler.py
phildb/reader.py
phildb/writer.py